Metadata-Version: 2.1
Name: python-io-wrapper
Version: 0.3
Summary: IO wrapper to add missing methods from io.BaseIO
Home-page: UNKNOWN
Author: David Megginson
Author-email: contact@megginson.io
License: UNKNOWN
Platform: UNKNOWN
